maupassant/__init__.py
maupassant/settings.py
maupassant/tensorflow_metric_loss_optimizer.py
maupassant/tensorflow_models_compile.py
maupassant/utils.py
maupassant/cluster/__init__.py
maupassant/cluster/clustering.py
maupassant/dataset/__init__.py
maupassant/dataset/labels.py
maupassant/dataset/pandas.py
maupassant/dataset/tensorflow.py
maupassant/feature_decomposition/__init__.py
maupassant/feature_decomposition/dimension_reduction.py
maupassant/feature_extraction/__init__.py
maupassant/feature_extraction/pretrained_embedding.py
maupassant/feature_extraction/tfidf.py
maupassant/preprocessing/__init__.py
maupassant/preprocessing/normalization.py
maupassant/preprocessing/tokenization.py
maupassant/stream_app/__init__.py
maupassant/stream_app/app.py
maupassant/stream_app/featuring.py
maupassant/stream_app/full_application.py
maupassant/stream_app/normalization.py
maupassant/stream_app/summarizer.py
maupassant/stream_app/trained_model.py
maupassant/tests/__init__.py
maupassant/tests/test_cluster.py
maupassant/tests/test_feature_extraction.py
maupassant/tests/test_preprocessing.py
maupassant/text_classification/__init__.py
maupassant/text_classification/dataset.py
maupassant/text_classification/predict.py
maupassant/text_classification/trainer.py
maupassant/text_generation/__init__.py
maupassant/text_generation/dataset.py
maupassant/text_generation/predict.py
maupassant/text_generation/trainer.py
maupassant/text_summarization/__init__.py
maupassant/text_summarization/dataset.py
maupassant/text_summarization/predict.py
maupassant/text_summarization/train.py
maupassant-0.1.1.dist-info/LICENSE
maupassant-0.1.1.dist-info/METADATA
maupassant-0.1.1.dist-info/WHEEL
maupassant-0.1.1.dist-info/top_level.txt
maupassant-0.1.1.dist-info/RECORD
