Metadata-Version: 2.1
Name: maupassant
Version: 0.1.1
Summary: UNKNOWN
Home-page: UNKNOWN
Author: UNKNOWN
Author-email: UNKNOWN
License: proprietary
Platform: UNKNOWN
Requires-Dist: tensorflow-gpu (==2.1.1)
Requires-Dist: tensorflow-hub (==0.7.0)
Requires-Dist: tensorflow-text (==2.1.1)
Requires-Dist: autocorrect (==2.0.0)
Requires-Dist: comet-ml (==3.2.0)
Requires-Dist: emot (==2.1)
Requires-Dist: nltk (==3.5)
Requires-Dist: pandas (==1.0.0)
Requires-Dist: pydot (==1.4.1)
Requires-Dist: pytest (==5.2.0)
Requires-Dist: scikit-learn (==0.23.0)
Requires-Dist: streamlit (==0.65.0)
Requires-Dist: umap-learn (==0.3.10)
Requires-Dist: contractions (==0.0.25)
Requires-Dist: python-dotenv (==0.14.0)
